rfc6902_types/__init__.py
rfc6902_types/py.typed
rfc6902_types-0.1.0.dist-info/LICENSE
rfc6902_types-0.1.0.dist-info/WHEEL
rfc6902_types-0.1.0.dist-info/METADATA
rfc6902_types-0.1.0.dist-info/RECORD
