Metadata-Version: 2.1
Name: rfc6902-types
Version: 0.1.0
Summary: Types aliases for RFC6902-compliant dicts
Author-email: Léo El Amri <leo@superlel.me>
Requires-Python: >=3.8
Classifier: License :: OSI Approved :: MIT License
